{
  "hash": "bfc81252",
  "configHash": "548c6720",
  "lockfileHash": "bf623032",
  "browserHash": "88d6cd6c",
  "optimized": {
    "react": {
      "src": "../../node_modules/react/index.js",
      "file": "react.js",
      "fileHash": "0d9d7df8",
      "needsInterop": true
    },
    "react-dom/client": {
      "src": "../../node_modules/react-dom/client.js",
      "file": "react-dom_client.js",
      "fileHash": "de666444",
      "needsInterop": true
    },
    "firebase/auth": {
      "src": "../../node_modules/firebase/auth/dist/esm/index.esm.js",
      "file": "firebase_auth.js",
      "fileHash": "73ade1a0",
      "needsInterop": false
    },
    "react-router-dom": {
      "src": "../../node_modules/react-router-dom/dist/index.js",
      "file": "react-router-dom.js",
      "fileHash": "ebe8f95d",
      "needsInterop": false
    },
    "firebase/app": {
      "src": "../../node_modules/firebase/app/dist/esm/index.esm.js",
      "file": "firebase_app.js",
      "fileHash": "35308366",
      "needsInterop": false
    },
    "axios": {
      "src": "../../node_modules/axios/index.js",
      "file": "axios.js",
      "fileHash": "c522690a",
      "needsInterop": false
    }
  },
  "chunks": {
    "chunk-TNTPHDQH": {
      "file": "chunk-TNTPHDQH.js"
    },
    "chunk-32E4H3EV": {
      "file": "chunk-32E4H3EV.js"
    },
    "chunk-YJK5K3R3": {
      "file": "chunk-YJK5K3R3.js"
    },
    "chunk-G3PMV62Z": {
      "file": "chunk-G3PMV62Z.js"
    }
  }
}